pytorch_tabnet/abstract_model.py
pytorch_tabnet/augmentations.py
pytorch_tabnet/callbacks.py
pytorch_tabnet/metrics.py
pytorch_tabnet/multiclass_utils.py
pytorch_tabnet/multitask.py
pytorch_tabnet/pretraining.py
pytorch_tabnet/pretraining_utils.py
pytorch_tabnet/sparsemax.py
pytorch_tabnet/tab_model.py
pytorch_tabnet/tab_network.py
pytorch_tabnet/utils.py
pytorch_tabnet-4.0.dist-info/LICENSE
pytorch_tabnet-4.0.dist-info/WHEEL
pytorch_tabnet-4.0.dist-info/METADATA
pytorch_tabnet-4.0.dist-info/RECORD
