Metadata-Version: 2.1
Name: pytorch-tabnet
Version: 4.0
Summary: PyTorch implementation of TabNet
Home-page: https://github.com/dreamquark-ai/tabnet
Keywords: tabnet,pytorch,neural-networks
Requires-Python: >=3.6
Classifier: Programming Language :: Python :: 3
Classifier: Programming Language :: Python :: 3.6
Classifier: Programming Language :: Python :: 3.7
Classifier: Programming Language :: Python :: 3.8
Classifier: Programming Language :: Python :: 3.9
Classifier: Programming Language :: Python :: 3.10
Requires-Dist: numpy (>=1.17,<2.0)
Requires-Dist: scikit_learn (>0.21)
Requires-Dist: scipy (>1.4)
Requires-Dist: torch (>=1.2,<2.0)
Requires-Dist: tqdm (>=4.36,<5.0)
Project-URL: Documentation, https://github.com/dreamquark-ai/tabnet
Project-URL: Repository, https://github.com/dreamquark-ai/tabnet
